kubernetes_wsgi/__init__.py
kubernetes_wsgi/__main__.py
kubernetes_wsgi/metrics.py
kubernetes_wsgi/server.py
kubernetes_wsgi-1.2.dist-info/LICENSE
kubernetes_wsgi-1.2.dist-info/METADATA
kubernetes_wsgi-1.2.dist-info/WHEEL
kubernetes_wsgi-1.2.dist-info/top_level.txt
kubernetes_wsgi-1.2.dist-info/RECORD
