Metadata-Version: 2.1
Name: kubernetes-wsgi
Version: 1.2
Summary: A wrapper for running your Python web application using Twisted in a way that works well for Kubernetes.
Home-page: https://github.com/coderanger/kubernetes-wsgi
License: Apache License 2.0
Classifier: License :: OSI Approved :: Apache Software License
Classifier: Programming Language :: Python :: 3
Classifier: Programming Language :: Python :: 3.5
Classifier: Programming Language :: Python :: 3.6
Classifier: Programming Language :: Python :: 3.7
Classifier: Programming Language :: Python :: 3.8
License-File: LICENSE
Requires-Dist: Twisted
Requires-Dist: prometheus-client
Provides-Extra: dev
Requires-Dist: pytest ; extra == 'dev'
Requires-Dist: requests ; extra == 'dev'
Provides-Extra: tests
Requires-Dist: pytest ; extra == 'tests'
Requires-Dist: requests ; extra == 'tests'
